auto_dev/__init__.py
auto_dev/base.py
auto_dev/behaviours/__init__.py
auto_dev/behaviours/protocol_scaffolder.py
auto_dev/behaviours/scaffolder.py
auto_dev/check_dependencies.py
auto_dev/cli.py
auto_dev/cli_executor.py
auto_dev/commands/__init__.py
auto_dev/commands/augment.py
auto_dev/commands/convert.py
auto_dev/commands/create.py
auto_dev/commands/create_from_fsm.py
auto_dev/commands/deps.py
auto_dev/commands/eject.py
auto_dev/commands/fmt.py
auto_dev/commands/fsm.py
auto_dev/commands/improve.py
auto_dev/commands/lint.py
auto_dev/commands/metadata.py
auto_dev/commands/publish.py
auto_dev/commands/release.py
auto_dev/commands/repo.py
auto_dev/commands/run.py
auto_dev/commands/scaffold.py
auto_dev/commands/test.py
auto_dev/commands/wf.py
auto_dev/connections/__init__.py
auto_dev/connections/scaffolder.py
auto_dev/constants.py
auto_dev/contracts/__init__.py
auto_dev/contracts/block_explorer.py
auto_dev/contracts/contract.py
auto_dev/contracts/contract_events.py
auto_dev/contracts/contract_functions.py
auto_dev/contracts/contract_scafolder.py
auto_dev/contracts/contract_templates.py
auto_dev/contracts/function.py
auto_dev/contracts/param_type.py
auto_dev/contracts/utils.py
auto_dev/contracts/variable.py
auto_dev/dao/__init__.py
auto_dev/dao/dummy_data.py
auto_dev/dao/generator.py
auto_dev/dao/scaffolder.py
auto_dev/data/__init__.py
auto_dev/data/aea-config.yaml
auto_dev/data/connections/__init__.py
auto_dev/data/connections/template.py
auto_dev/data/connections/test_template.py
auto_dev/data/contracts/__init__.py
auto_dev/data/contracts/header.py
auto_dev/data/fsm/samples/fsm_specification.yaml
auto_dev/data/mapping.txt
auto_dev/data/mermaid.py
auto_dev/data/openapi/openapi_specification.yaml
auto_dev/data/openapi/skill.yaml
auto_dev/data/protocols/examples/balances.yaml
auto_dev/data/repo/templates/autonomy/.env.template
auto_dev/data/repo/templates/autonomy/.env.template.template
auto_dev/data/repo/templates/autonomy/.github/workflows/common_check.yaml
autonomy_dev-0.2.161.dist-info/LICENSE
autonomy_dev-0.2.161.dist-info/METADATA
autonomy_dev-0.2.161.dist-info/WHEEL
autonomy_dev-0.2.161.dist-info/entry_points.txt
autonomy_dev-0.2.161.dist-info/RECORD
