Metadata-Version: 2.3
Name: autonomy_dev
Version: 0.2.161
Summary: A collection of tooling to enable open source development of autonomy tools
License: Apache-2.0
Author: 8Baller
Author-email: 8ball030@gmail.com
Requires-Python: >=3.10,<3.13
Classifier: Development Status :: 2 - Pre-Alpha
Classifier: Intended Audience :: Developers
Classifier: License :: OSI Approved :: Apache Software License
Classifier: Natural Language :: English
Classifier: Programming Language :: Python :: 3
Classifier: Programming Language :: Python :: 3.10
Classifier: Programming Language :: Python :: 3.11
Classifier: Programming Language :: Python :: 3.12
Provides-Extra: all
Requires-Dist: asn1crypto (>=1.4.0,<1.5.0)
Requires-Dist: disutils (>=1.4.32.post2,<2.0.0)
Requires-Dist: grpcio (==1.69.0)
Requires-Dist: hypothesis (==6.122.3)
Requires-Dist: ipfshttpclient (==0.8.0a2)
Requires-Dist: isort (>=5.13.2,<6.0.0) ; extra == "all"
Requires-Dist: open-aea-cli-ipfs (==2.0.6)
Requires-Dist: open-aea-ledger-cosmos (==2.0.6) ; extra == "all"
Requires-Dist: open-aea-ledger-ethereum (==2.0.6) ; extra == "all"
Requires-Dist: open-aea-test-autonomy (==0.21.5)
Requires-Dist: open-aea[all] (==2.0.6) ; extra == "all"
Requires-Dist: open-autonomy (==0.21.5) ; extra == "all"
Requires-Dist: openapi-spec-validator (==0.2.8)
Requires-Dist: proto-schema-parser (>=1.5.0,<2.0.0)
Requires-Dist: protobuf (>=3.19.1,<4.25.0)
Requires-Dist: py-eth-sig-utils
Requires-Dist: py-multibase (==1.0.3)
Requires-Dist: py-multicodec (==0.2.1)
Requires-Dist: pycryptodome (==3.20.0)
Requires-Dist: pydantic (>=2.8.2,<3.0.0) ; extra == "all"
Requires-Dist: pydoclint[all] (>=0.6.0,<0.7.0) ; extra == "all"
Requires-Dist: pytest-xdist (>=3.6.1,<4.0.0)
Requires-Dist: requests (>=2.28.1,<3)
Requires-Dist: rich-click (>=1.8.2,<2.0.0)
Requires-Dist: ruff (>=0.5.7,<0.6.0) ; extra == "all"
Requires-Dist: setuptools (>=75.8.0,<76.0.0) ; extra == "all"
Requires-Dist: tbump (>=6.11.0,<7.0.0) ; extra == "all"
Requires-Dist: toml (==0.10.2)
Requires-Dist: tomte[all] (==0.4.0)
Requires-Dist: typing_extensions (>=3.10.0.2)
Requires-Dist: web3 (>=6.0.0,<8.0.0)
Project-URL: Homepage, https://github.com/8ball030/auto_dev
